COPYING
LICENSE
MANIFEST.in
setup.py
test.py
docs/StringIO-module.html
docs/StringIO-pysrc.html
docs/StringIO.StringIO-class.html
docs/class-tree.html
docs/crarr.png
docs/epydoc.css
docs/epydoc.js
docs/frames.html
docs/help.html
docs/identifier-index.html
docs/index.html
docs/module-tree.html
docs/spoon-module.html
docs/spoon-pysrc.html
docs/spoon.NullLogger'-module.html
docs/spoon.NullLogger'-pysrc.html
docs/spoon.NullLogger-class.html
docs/spoon.Serial-class.html
docs/spoon.SpoonStream-class.html
docs/spoon.ber-module.html
docs/spoon.ber-pysrc.html
docs/spoon.ber.BERException-class.html
docs/spoon.ber.BERStream-class.html
docs/spoon.ber.Tag-class.html
docs/spoon.ber.common-module.html
docs/spoon.ber.common-pysrc.html
docs/spoon.ber.common.BERException-class.html
docs/spoon.ber.decoder-class.html
docs/spoon.ber.encoder-class.html
docs/spoon.ber.stream-module.html
docs/spoon.ber.stream-pysrc.html
docs/spoon.ber.stream.BERStream-class.html
docs/spoon.ber.stream.CountingFile-class.html
docs/spoon.ber.stream.decoder-class.html
docs/spoon.ber.stream.encoder-class.html
docs/spoon.ber.stream.zencoder-class.html
docs/spoon.ber.tag-module.html
docs/spoon.ber.tag-pysrc.html
docs/spoon.ber.tag.Tag-class.html
docs/spoon.ber.zencoder-class.html
docs/spoon.lazyprop-class.html
docs/spoon.messaging-module.html
docs/spoon.messaging-pysrc.html
docs/spoon.messaging.Messaging-class.html
docs/spoon.messaging.SingletonMessaging-class.html
docs/spoon.messaging.decorators-module.html
docs/spoon.messaging.decorators-pysrc.html
docs/spoon.messaging.decorators.receive-class.html
docs/spoon.messaging.messaging-module.html
docs/spoon.messaging.messaging-pysrc.html
docs/spoon.messaging.messaging.Messaging-class.html
docs/spoon.messaging.messaging.SingletonMessaging-class.html
docs/spoon.messaging.messagingcore-module.html
docs/spoon.messaging.messagingcore-pysrc.html
docs/spoon.messaging.messagingcore.Messaging-class.html
docs/spoon.messaging.messagingcore.SingletonMessaging-class.html
spoonrpc.egg-info/PKG-INFO
spoonrpc.egg-info/SOURCES.txt
spoonrpc.egg-info/dependency_links.txt
spoonrpc.egg-info/top_level.txt
